Taoufiq/__init__.py
Taoufiq/example.py
package_taoufiq-0.0.1.dist-info/LICENSE.txt
package_taoufiq-0.0.1.dist-info/METADATA
package_taoufiq-0.0.1.dist-info/WHEEL
package_taoufiq-0.0.1.dist-info/top_level.txt
package_taoufiq-0.0.1.dist-info/RECORD
