Metadata-Version: 2.1
Name: package_taoufiq
Version: 0.0.1
Summary: A small example package
Author-email: Samad88 <samadtaoufik@gmail.com>
Project-URL: Homepage, https://github.com/pypa/sampleproject
Project-URL: Issues, https://github.com/pypa/sampleproject/issues
Classifier: Programming Language :: Python :: 3
Classifier: License :: OSI Approved :: MIT License
Classifier: Operating System :: OS Independent
Requires-Python: >=3.9
License-File: LICENSE.txt
Requires-Dist: google-api-python-client
Requires-Dist: matplotlib
